README.md
setup.py
TOPSIS_Yashika_401803010.egg-info/PKG-INFO
TOPSIS_Yashika_401803010.egg-info/SOURCES.txt
TOPSIS_Yashika_401803010.egg-info/dependency_links.txt
TOPSIS_Yashika_401803010.egg-info/entry_points.txt
TOPSIS_Yashika_401803010.egg-info/requires.txt
TOPSIS_Yashika_401803010.egg-info/top_level.txt
src/topsis.py